{
  "students": [
    {
      "id": "1668534472527",
      "firstName": "Ali",
      "lastName": "Yılmaz",
      "gender": "Erkek",
      "number": "106",
      "school": "React-Redux İlköğretim Okulu",
      "class": "5/B",
      "hobbys": [
        "Kitap Okumak",
        "Tenis Oynamak",
        "Bisiklet Kullanmak",
        "Seyahat Etmek"
      ],
      "booksread": [
        "Çizgili Pijamalı Çocuk-John Boyne",
        "Alice Harikalar Diyarında-Lewis Carrol",
        "Son Adanın Çocukları-Zülfi Livaneli"
      ]
    },
    {
      "id": "1668853637060",
      "firstName": "Yasin",
      "lastName": "Okuyan",
      "gender": "Erkek",
      "number": "23",
      "school": "React-Redux İlköğretim Okulu",
      "class": "5/B",
      "hobbys": [
        "Bisiklet Kullanmak",
        "Tenis Oynamak"
      ],
      "booksread": [
        "Alice Harikalar Diyarında-Lewis Carrol",
        "Son Adanın Çocukları-Zülfi Livaneli"
      ]
    },
    {
      "id": "1668853796795",
      "firstName": "Hülya",
      "lastName": "Kaya",
      "gender": "Kız",
      "number": "43",
      "school": "React-Redux İlköğretim Okulu",
      "class": "4/B",
      "hobbys": [
        "Tenis Oynamak",
        "Resim Yapmak",
        "Kitap Okumak",
        "Satranç Oynamak"
      ],
      "booksread": [
        "80 Günde Devri Alem-Jules Verne",
        "Sefiller-Victor Hugo",
        "Troya Masalı-Azra Erhat",
        "Beyaz Diş-Jack London",
        "Alice Harikalar Diyarında-Lewis Carrol"
      ]
    },
    {
      "id": "1668854001762",
      "firstName": "Kemalettin",
      "lastName": "Yolgiden",
      "gender": "Erkek",
      "number": "25",
      "school": "React-Redux İlköğretim Okulu",
      "class": "5/A",
      "hobbys": [
        "Seyahat Etmek",
        "Kitap Okumak",
        "Yüzmek",
        "Bisiklet Kullanmak"
      ],
      "booksread": [
        "Beyaz Diş-Jack London",
        "Troya Masalı-Azra Erhat",
        "Alice Harikalar Diyarında-Lewis Carrol",
        "Pal Sokağı Çocukları-Ferenc Molnar"
      ]
    },
    {
      "id": "1668855125390",
      "firstName": "Zeynel",
      "lastName": "Korucu",
      "gender": "Erkek",
      "number": "10",
      "school": "React-Redux İlköğretim Okulu",
      "class": "5/A",
      "hobbys": [
        "Resim Yapmak",
        "Kitap Okumak",
        "Seyahat Etmek",
        "Yüzmek"
      ],
      "booksread": [
        "Çizgili Pijamalı Çocuk-John Boyne",
        "Beyaz Diş-Jack London",
        "Troya Masalı-Azra Erhat"
      ]
    },
    {
      "id": "1669014120745",
      "firstName": "Zehra",
      "lastName": "Özbek",
      "gender": "Kız",
      "number": "1001",
      "school": "React-Redux İlköğretim Okulu",
      "class": "4/A",
      "hobbys": [
        "Fotoğrafçılık",
        "Resim Yapmak",
        "Yüzmek",
        "Bisiklet Kullanmak",
        "Seyahat Etmek"
      ],
      "booksread": [
        "Çizgili Pijamalı Çocuk-John Boyne",
        "Sefiller-Victor Hugo",
        "Son Adanın Çocukları-Zülfi Livaneli",
        "Alice Harikalar Diyarında-Lewis Carrol"
      ]
    },
    {
      "id": "1669014175699",
      "firstName": "Aysel",
      "lastName": "Temelli",
      "gender": "Kız",
      "number": "1002",
      "school": "React-Redux İlköğretim Okulu",
      "class": "4/A",
      "hobbys": [
        "Yüzmek",
        "Tenis Oynamak",
        "Resim Yapmak"
      ],
      "booksread": [
        "Beyaz Diş-Jack London",
        "Çizgili Pijamalı Çocuk-John Boyne",
        "Troya Masalı-Azra Erhat"
      ]
    },
    {
      "id": "1669014307151",
      "firstName": "Alev",
      "lastName": "Cingöz",
      "gender": "Kız",
      "number": "1003",
      "school": "React-Redux İlköğretim Okulu",
      "class": "5/A",
      "hobbys": [
        "Tenis Oynamak",
        "Seyahat Etmek",
        "Fotoğrafçılık"
      ],
      "booksread": [
        "80 Günde Devri Alem-Jules Verne"
      ]
    },
    {
      "id": "1669021827403",
      "firstName": "Zekeriya",
      "lastName": "Duman",
      "gender": "Erkek",
      "number": "1004",
      "school": "React-Redux İlköğretim Okulu",
      "class": "4/B",
      "hobbys": [
        "Kitap Okumak",
        "Resim Yapmak"
      ],
      "booksread": [
        "Beyaz Diş-Jack London"
      ]
    },
    {
      "id": "1669232502035",
      "firstName": "Orhan",
      "lastName": "Ayaz",
      "gender": "Erkek",
      "number": "1009",
      "school": "React-Redux İlköğretim Okulu",
      "class": "2/B",
      "hobbys": [
        "Tenis Oynamak",
        "Bisiklet Kullanmak"
      ],
      "booksread": [
        "Alice Harikalar Diyarında-Lewis Carrol",
        "Son Adanın Çocukları-Zülfi Livaneli"
      ]
    },
    {
      "id": "1669272052674",
      "firstName": "Hakan",
      "lastName": "Çubukçu",
      "gender": "Erkek",
      "number": "1012",
      "school": "React-Redux İlköğretim Okulu",
      "class": "4/C",
      "hobbys": [
        "Satranç Oynamak",
        "Fotoğrafçılık",
        "Seyahat Etmek",
        "Kitap Okumak"
      ],
      "booksread": []
    },
    {
      "id": "1669272544571",
      "firstName": "Türkan",
      "lastName": "Aygün",
      "gender": "Kız",
      "number": "1016",
      "school": "React-Redux İlköğretim Okulu",
      "class": "4/B",
      "hobbys": [
        "Satranç Oynamak",
        "Fotoğrafçılık",
        "Seyahat Etmek",
        "Kitap Okumak",
        "Resim Yapmak"
      ],
      "booksread": [
        "Son Adanın Çocukları-Zülfi Livaneli",
        "Pal Sokağı Çocukları-Ferenc Molnar"
      ]
    },
    {
      "id": "1669272735626",
      "firstName": "Nalan",
      "lastName": "Pekuysal",
      "gender": "Kız",
      "number": "1017",
      "school": "React-Redux İlköğretim Okulu",
      "class": "5/B",
      "hobbys": [
        "Yüzmek",
        "Bisiklet Kullanmak",
        "Tenis Oynamak",
        "Resim Yapmak",
        "Kitap Okumak",
        "Fotoğrafçılık",
        "Seyahat Etmek"
      ],
      "booksread": [
        "Beyaz Diş-Jack London",
        "Son Adanın Çocukları-Zülfi Livaneli"
      ]
    },
    {
      "id": "1669275630159",
      "firstName": "Ayten",
      "lastName": "Canlı",
      "gender": "Kız",
      "number": "1013",
      "school": "React-Redux İlköğretim Okulu",
      "class": "5/B",
      "hobbys": [
        "Kitap Okumak",
        "Seyahat Etmek",
        "Yüzmek"
      ],
      "booksread": [
        "Troya Masalı-Azra Erhat",
        "Alice Harikalar Diyarında-Lewis Carrol"
      ]
    },
    {
      "id": "1669275964236",
      "firstName": "Enes",
      "lastName": "Atik",
      "gender": "Erkek",
      "number": "1015",
      "school": "React-Redux İlköğretim Okulu",
      "class": "5/B",
      "hobbys": [
        "Satranç Oynamak",
        "Yüzmek",
        "Fotoğrafçılık",
        "Bisiklet Kullanmak"
      ],
      "booksread": [
        "Alice Harikalar Diyarında-Lewis Carrol",
        "Beyaz Diş-Jack London"
      ]
    },
    {
      "id": "1669276302608",
      "firstName": "Özge meryem",
      "lastName": "Öztürk",
      "gender": "Kız",
      "number": "1020",
      "school": "React-Redux İlköğretim Okulu",
      "class": "5/B",
      "hobbys": [
        "Kitap Okumak",
        "Resim Yapmak",
        "Fotoğrafçılık"
      ],
      "booksread": [
        "80 Günde Devri Alem-Jules Verne",
        "Beyaz Diş-Jack London",
        "Son Adanın Çocukları-Zülfi Livaneli"
      ]
    },
    {
      "id": "1669450764041",
      "firstName": "Nursel yade",
      "lastName": "Güldüren",
      "gender": "Kız",
      "number": "1021",
      "school": "React-Redux İlköğretim Okulu",
      "class": "5/A",
      "hobbys": [
        "Resim Yapmak",
        "Tenis Oynamak",
        "Yüzmek"
      ],
      "booksread": [
        "Çizgili Pijamalı Çocuk-John Boyne",
        "Troya Masalı-Azra Erhat",
        "Alice Harikalar Diyarında-Lewis Carrol"
      ]
    },
    {
      "id": "1669457556539",
      "firstName": "Ceyda",
      "lastName": "Hasanlar",
      "gender": "Kız",
      "number": "1023",
      "school": "React-Redux İlköğretim Okulu",
      "class": "4/A",
      "hobbys": [
        "Fotoğrafçılık"
      ],
      "booksread": [
        "Çizgili Pijamalı Çocuk-John Boyne",
        "Beyaz Diş-Jack London"
      ]
    },
    {
      "id": "1669459214199",
      "firstName": "Meltem Nur",
      "lastName": "Bilgili",
      "gender": "Kız",
      "number": "1075",
      "school": "React-Redux İlköğretim Okulu",
      "class": "5/A",
      "hobbys": [
        "Kitap Okumak",
        "Resim Yapmak"
      ],
      "booksread": [
        "Sefiller-Victor Hugo",
        "80 Günde Devri Alem-Jules Verne"
      ]
    },
    {
      "id": "1669459362132",
      "firstName": "Irfan Sami̇ Orhan",
      "lastName": "Ayan Kara",
      "gender": "Erkek",
      "number": "1029",
      "school": "React-Redux İlköğretim Okulu",
      "class": "4/B",
      "hobbys": [
        "Fotoğrafçılık",
        "Seyahat Etmek"
      ],
      "booksread": [
        "Beyaz Diş-Jack London",
        "Troya Masalı-Azra Erhat"
      ]
    },
    {
      "id": "1669460029730",
      "firstName": "Mehmet Ali",
      "lastName": "Candan Aydin",
      "gender": "Erkek",
      "number": "1089",
      "school": "React-Redux İlköğretim Okulu",
      "class": "5/B",
      "hobbys": [
        "Resim Yapmak"
      ],
      "booksread": [
        "Alice Harikalar Diyarında-Lewis Carrol",
        "Troya Masalı-Azra Erhat"
      ]
    },
    {
      "id": "1675257699891",
      "firstName": "Aydın Cem",
      "lastName": "Kocatürk",
      "gender": "Erkek",
      "number": "111",
      "school": "React-Redux İlköğretim Okulu",
      "class": "3/A",
      "hobbys": [
        "Seyahat Etmek",
        "Fotoğrafçılık",
        "Tenis Oynamak"
      ],
      "booksread": [
        "Troya Masalı-Azra Erhat",
        "Çizgili Pijamalı Çocuk-John Boyne",
        "Sefiller-Victor Hugo"
      ]
    }
  ],
  "hobby_list": [
    "Satranç Oynamak",
    "Fotoğrafçılık",
    "Seyahat Etmek",
    "Kitap Okumak",
    "Resim Yapmak",
    "Tenis Oynamak",
    "Bisiklet Kullanmak",
    "Yüzmek"
  ],
  "books": [
    "80 Günde Devri Alem-Jules Verne",
    "Sefiller-Victor Hugo",
    "Çizgili Pijamalı Çocuk-John Boyne",
    "Beyaz Diş-Jack London",
    "Troya Masalı-Azra Erhat",
    "Alice Harikalar Diyarında-Lewis Carrol",
    "Son Adanın Çocukları-Zülfi Livaneli",
    "Pal Sokağı Çocukları-Ferenc Molnar"
  ],
  "classlist": [
    "1/A",
    "1/B",
    "2/A",
    "2/B",
    "3/A",
    "3/B",
    "3/C",
    "4/A",
    "4/B",
    "4/C",
    "5/A",
    "5/B",
    "5/C"
  ]
}